pyleaf/ReadBarcodes.py
pyleaf/__init__.py
pyleaf/basefunctions.py
pyleaf/leaf_area_calculator_gui.py
pyleaf/leaf_top.png
pyleaf/model.h5
pyleaf/model.json
pyleaf/pyleaf.pdf
pyleaf/limited_test_images/IMG_7224.JPG
pyleaf/limited_test_images/IMG_7225.JPG
pyleaf/limited_test_images/SF17-BE-p0007-r1_IMG_9375.JPG
pyleaf/limited_test_images/SF17-BE-p0019-r1_IMG_7005.JPG
pyleaf/limited_test_images/SF17-BE-p0019-r3_IMG_7002.JPG
pyleaf/limited_test_images/SF17-BE-p0023-r2_IMG_7169.JPG
pyleaf/limited_test_images/SF17-BE-p0047-r1_IMG_7922.JPG
pyleaf/limited_test_images/SF17-BE-p0047-r3_IMG_7919.JPG
pyleaf/saved_images/IMG_7224.JPG
pyleaf/test_images/envelope_19.png
pyleaf/test_images/green_4.png
pyleaf/test_images/red.png
pyleaf/test_images/red2.png
pyleaf/test_images/white.png
pyleaf/test_images/white_1.png
pyleaf/tests/__init__.py
pyleaf/tests/test_leafAreaCalculatorGUI.py
pyleafarea-2.3.1.dist-info/LICENSE.txt
pyleafarea-2.3.1.dist-info/METADATA
pyleafarea-2.3.1.dist-info/WHEEL
pyleafarea-2.3.1.dist-info/top_level.txt
pyleafarea-2.3.1.dist-info/RECORD
