Metadata-Version: 2.1
Name: pyleafarea
Version: 2.3.1
Summary: Automated Leaf Area Calculator Using Tkinter and Deep Learning Image Classification Model.
Home-page: 
Author: Vishal Sonawane, Balasaheb Sonawane, Joseph Crawford
Author-email: vishalsonawane1515@gmail.com, balasahebsonawane@gmail.com, joseph.crawford@wsu.edu
License: MIT License
License-File: LICENSE.txt
Requires-Dist: tensorflow (>=2.2.0)
Requires-Dist: tensorboard (>=2.2.0)
Requires-Dist: keras-preprocessing
Requires-Dist: absl-py
Requires-Dist: setuptools
Requires-Dist: pandas
Requires-Dist: Pillow
Requires-Dist: opt-einsum
Requires-Dist: astunparse
Requires-Dist: protobuf
Requires-Dist: pyzbar
Requires-Dist: pyasn1
Requires-Dist: opencv-python
